{
    "org": {
        "sql": "SELECT users.* FROM users WHERE LOWER(users.login) LIKE LOWER('%jsmi%') OR users.id IN (SELECT user_id FROM email_addresses WHERE LOWER(address) LIKE LOWER('%jsmi%')) OR LOWER(users.firstname) LIKE LOWER('%jsmi%') OR LOWER(users.lastname) LIKE LOWER('%jsmi%')",
        "cost": 718.64,
        "rewrite_types": []
    },
    "rewrites": [
        {
            "sql": "SELECT users.* FROM users WHERE LOWER(users.login) LIKE LOWER('%jsmi%') OR users.id IN (SELECT user_id FROM email_addresses WHERE LOWER(address) LIKE LOWER('%jsmi%') LIMIT 1) OR LOWER(users.firstname) LIKE LOWER('%jsmi%') OR LOWER(users.lastname) LIKE LOWER('%jsmi%') LIMIT 1",
            "cost": 3.49,
            "rewrite_types": [
                "AddLimitOne"
            ]
        },
        {
            "sql": "SELECT users.* FROM users WHERE LOWER(users.login) LIKE LOWER('%jsmi%') OR users.id IN (SELECT user_id FROM email_addresses WHERE LOWER(address) LIKE LOWER('%jsmi%')) OR LOWER(users.firstname) LIKE LOWER('%jsmi%') OR LOWER(users.lastname) LIKE LOWER('%jsmi%') LIMIT 1",
            "cost": 148.58,
            "rewrite_types": [
                "AddLimitOne"
            ]
        },
        {
            "sql": "SELECT users.* FROM users WHERE LOWER(users.login) LIKE LOWER('%jsmi%') OR users.id IN (SELECT user_id FROM email_addresses WHERE LOWER(address) LIKE LOWER('%jsmi%') LIMIT 1) OR LOWER(users.firstname) LIKE LOWER('%jsmi%') OR LOWER(users.lastname) LIKE LOWER('%jsmi%')",
            "cost": 573.55,
            "rewrite_types": [
                "AddLimitOne"
            ]
        }
    ]
}