{
    "org": {
        "sql": "SELECT 1 AS one FROM diary_entries INNER JOIN users ON users.id = diary_entries.user_id LEFT OUTER JOIN languages ON languages.code = diary_entries.language_code WHERE users.status IN (\"$1\", \"$2\") AND diary_entries.visible = \"$3\" LIMIT \"$4\" OFFSET \"$5\"",
        "cost": 2.33,
        "rewrite_types": []
    },
    "rewrites": [
        {
            "sql": "SELECT 1 AS one FROM diary_entries LEFT OUTER JOIN languages ON languages.code = diary_entries.language_code WHERE diary_entries.visible = \"$3\" LIMIT \"$4\" OFFSET \"$5\"",
            "cost": 0.23,
            "rewrite_types": [
                "RemoveJoin"
            ]
        },
        {
            "sql": "SELECT 1 AS one FROM diary_entries LEFT OUTER JOIN languages ON languages.code = diary_entries.language_code WHERE diary_entries.visible = \"$3\" LIMIT \"$4\" OFFSET \"$5\"",
            "cost": 0.23,
            "rewrite_types": [
                "RemoveJoin"
            ]
        },
        {
            "sql": "SELECT 1 AS one FROM diary_entries INNER JOIN languages ON languages.code = diary_entries.language_code WHERE diary_entries.visible = \"$3\" LIMIT \"$4\" OFFSET \"$5\"",
            "cost": 1.26,
            "rewrite_types": [
                "RemoveJoin",
                "ReplaceOuterJoin"
            ]
        },
        {
            "sql": "SELECT 1 AS one FROM diary_entries INNER JOIN languages ON languages.code = diary_entries.language_code WHERE diary_entries.visible = \"$3\" LIMIT \"$4\" OFFSET \"$5\"",
            "cost": 1.26,
            "rewrite_types": [
                "RemoveJoin",
                "ReplaceOuterJoin"
            ]
        }
    ]
}