{
    "org": {
        "sql": "SELECT 1 AS one FROM relations WHERE relations.from_id = \"$1\" AND relations.to_id = \"$2\" AND relations.id IS NOT NULL LIMIT 1",
        "cost": 8.3,
        "rewrite_types": []
    },
    "rewrites": [
        {
            "sql": "SELECT 1 AS one FROM relations WHERE relations.from_id = \"$1\" AND relations.to_id = \"$2\" AND True LIMIT 1",
            "cost": 8.3,
            "rewrite_types": [
                "RewriteNullPredicate"
            ]
        }
    ]
}