{"schemas": [{"name": "journals", "fields": ["id", "journable_type", "journable_id", "user_id", "notes", "created_at", "version", "data_type", "data_id"], "types": ["INTEGER", "VARCHAR", "INTEGER", "INTEGER", "VARCHAR", "TIMESTAMP", "INTEGER", "VARCHAR", "BIGINT"], "nullable": [false, true, false, false, true, false, false, true, false], "key": [[8, 7], [1, 2, 6], [6, 2, 1], [0]], "foreign": [], "guaranteed": []}, {"name": "changeset_journals", "fields": ["id", "repository_id", "revision", "committed_on", "comments"], "types": ["INTEGER", "INTEGER", "VARCHAR", "TIMESTAMP", "VARCHAR"], "nullable": [false, false, false, false, true], "key": [], "foreign": [], "guaranteed": []}, {"name": "repositories", "fields": ["id", "project_id", "type"], "types": ["INTEGER", "INTEGER", "VARCHAR"], "nullable": [false, false, true], "key": [[1], [0]], "foreign": [], "guaranteed": []}, {"name": "projects", "fields": ["id", "name", "description", "public", "parent_id", "created_at", "updated_at", "identifier", "lft", "rgt", "active", "templated"], "types": ["INTEGER", "VARCHAR", "VARCHAR", "BOOLEAN", "INTEGER", "TIMESTAMP", "TIMESTAMP", "VARCHAR", "INTEGER", "INTEGER", "BOOLEAN", "BOOLEAN"], "nullable": [false, false, true, false, true, true, true, true, true, true, false, false], "key": [[7], [0]], "foreign": [], "guaranteed": []}, {"name": "enabled_modules", "fields": ["id", "project_id", "name"], "types": ["INTEGER", "INTEGER", "VARCHAR"], "nullable": [false, false, false], "key": [[2, 1], [0]], "foreign": [], "guaranteed": []}], "queries": [{"sort": {"collation": [[0, "INTEGER", "DESC"]], "limit": {"operator": "10", "operand": [], "type": "INTEGER"}, "source": {"project": {"target": [{"column": 0, "type": "INTEGER"}, {"column": 5, "type": "TIMESTAMP"}, {"column": 3, "type": "INTEGER"}, {"column": 4, "type": "VARCHAR"}, {"column": 6, "type": "INTEGER"}, {"column": 2, "type": "INTEGER"}, {"column": 11, "type": "VARCHAR"}, {"column": 13, "type": "VARCHAR"}, {"column": 12, "type": "TIMESTAMP"}, {"column": 15, "type": "INTEGER"}, {"column": 16, "type": "VARCHAR"}], "source": {"filter": {"condition": {"operator": "AND", "operand": [{"operator": "=", "operand": [{"column": 1, "type": "VARCHAR"}, {"operator": "_ISO-8859-1'Changeset'", "operand": [], "type": "VARCHAR"}], "type": "BOOLEAN"}, {"operator": "=", "operand": [{"column": 3, "type": "INTEGER"}, {"operator": "653", "operand": [], "type": "INTEGER"}], "type": "BOOLEAN"}, {"operator": "IN", "operand": [{"column": 17, "type": "INTEGER"}], "query": {"project": {"target": [{"column": 19, "type": "INTEGER"}], "source": {"filter": {"condition": {"operator": "=", "operand": [{"column": 20, "type": "VARCHAR"}, {"operator": "_ISO-8859-1'activity'", "operand": [], "type": "VARCHAR"}], "type": "BOOLEAN"}, "source": {"scan": 4}}}}}, "type": "BOOLEAN"}, {"operator": "IN", "operand": [{"column": 17, "type": "INTEGER"}], "query": {"distinct": {"correlate": [{"project": {"target": [{"column": 18, "type": "INTEGER"}], "source": {"project": {"target": [{"column": 18, "type": "INTEGER"}], "source": {"filter": {"condition": {"operator": "=", "operand": [{"column": 28, "type": "BOOLEAN"}, {"operator": "true", "operand": [], "type": "BOOLEAN"}], "type": "BOOLEAN"}, "source": {"join": {"kind": "INNER", "condition": {"operator": "AND", "operand": [{"operator": "=", "operand": [{"column": 18, "type": "INTEGER"}, {"column": 31, "type": "INTEGER"}], "type": "BOOLEAN"}, {"operator": "=", "operand": [{"column": 32, "type": "VARCHAR"}, {"operator": "_ISO-8859-1'repository'", "operand": [], "type": "CHAR"}], "type": "BOOLEAN"}, {"operator": "=", "operand": [{"column": 28, "type": "BOOLEAN"}, {"operator": "true", "operand": [], "type": "BOOLEAN"}], "type": "BOOLEAN"}], "type": "BOOLEAN"}, "left": {"scan": 3}, "right": {"scan": 4}}}}}}}}}, {"aggregate": {"function": [], "source": {"filter": {"condition": {"operator": "AND", "operand": [{"operator": "=", "operand": [{"column": 18, "type": "INTEGER"}, {"column": 19, "type": "INTEGER"}], "type": "BOOLEAN"}], "type": "BOOLEAN"}, "source": {"project": {"target": [{"column": 19, "type": "INTEGER"}], "source": {"filter": {"condition": {"operator": "=", "operand": [{"column": 29, "type": "BOOLEAN"}, {"operator": "true", "operand": [], "type": "BOOLEAN"}], "type": "BOOLEAN"}, "source": {"join": {"kind": "INNER", "condition": {"operator": "AND", "operand": [{"operator": "=", "operand": [{"column": 19, "type": "INTEGER"}, {"column": 32, "type": "INTEGER"}], "type": "BOOLEAN"}, {"operator": "=", "operand": [{"column": 33, "type": "VARCHAR"}, {"operator": "_ISO-8859-1'repository'", "operand": [], "type": "CHAR"}], "type": "BOOLEAN"}, {"operator": "=", "operand": [{"column": 29, "type": "BOOLEAN"}, {"operator": "true", "operand": [], "type": "BOOLEAN"}], "type": "BOOLEAN"}], "type": "BOOLEAN"}, "left": {"scan": 3}, "right": {"scan": 4}}}}}}}}}}}]}}, "type": "BOOLEAN"}], "type": "BOOLEAN"}, "source": {"join": {"kind": "INNER", "condition": {"operator": "=", "operand": [{"column": 17, "type": "INTEGER"}, {"column": 15, "type": "INTEGER"}], "type": "BOOLEAN"}, "left": {"join": {"kind": "INNER", "condition": {"operator": "=", "operand": [{"column": 10, "type": "INTEGER"}, {"column": 14, "type": "INTEGER"}], "type": "BOOLEAN"}, "left": {"join": {"kind": "INNER", "condition": {"operator": "AND", "operand": [{"operator": "=", "operand": [{"column": 8, "type": "BIGINT"}, {"operator": "CAST", "operand": [{"column": 9, "type": "INTEGER"}], "type": "BIGINT"}], "type": "BOOLEAN"}, {"operator": "=", "operand": [{"column": 7, "type": "VARCHAR"}, {"operator": "_ISO-8859-1'Journal::ChangesetJournal'", "operand": [], "type": "VARCHAR"}], "type": "BOOLEAN"}], "type": "BOOLEAN"}, "left": {"scan": 0}, "right": {"scan": 1}}}, "right": {"scan": 2}}}, "right": {"project": {"target": [{"column": 0, "type": "INTEGER"}], "source": {"scan": 3}}}}}}}}}}}, {"sort": {"collation": [[0, "INTEGER", "DESC"]], "limit": {"operator": "10", "operand": [], "type": "INTEGER"}, "source": {"project": {"target": [{"column": 0, "type": "INTEGER"}, {"column": 5, "type": "TIMESTAMP"}, {"column": 3, "type": "INTEGER"}, {"column": 4, "type": "VARCHAR"}, {"column": 6, "type": "INTEGER"}, {"column": 2, "type": "INTEGER"}, {"column": 11, "type": "VARCHAR"}, {"column": 13, "type": "VARCHAR"}, {"column": 12, "type": "TIMESTAMP"}, {"column": 15, "type": "INTEGER"}, {"column": 16, "type": "VARCHAR"}], "source": {"filter": {"condition": {"operator": "AND", "operand": [{"operator": "=", "operand": [{"column": 1, "type": "VARCHAR"}, {"operator": "_ISO-8859-1'Changeset'", "operand": [], "type": "VARCHAR"}], "type": "BOOLEAN"}, {"operator": "=", "operand": [{"column": 3, "type": "INTEGER"}, {"operator": "653", "operand": [], "type": "INTEGER"}], "type": "BOOLEAN"}, {"operator": "IN", "operand": [{"column": 17, "type": "INTEGER"}], "query": {"sort": {"collation": [], "limit": {"operator": "1", "operand": [], "type": "INTEGER"}, "source": {"project": {"target": [{"column": 19, "type": "INTEGER"}], "source": {"filter": {"condition": {"operator": "=", "operand": [{"column": 20, "type": "VARCHAR"}, {"operator": "_ISO-8859-1'activity'", "operand": [], "type": "VARCHAR"}], "type": "BOOLEAN"}, "source": {"scan": 4}}}}}}}, "type": "BOOLEAN"}, {"operator": "IN", "operand": [{"column": 17, "type": "INTEGER"}], "query": {"sort": {"collation": [], "limit": {"operator": "1", "operand": [], "type": "INTEGER"}, "source": {"project": {"target": [{"column": 18, "type": "INTEGER"}], "source": {"filter": {"condition": {"operator": "=", "operand": [{"column": 28, "type": "BOOLEAN"}, {"operator": "true", "operand": [], "type": "BOOLEAN"}], "type": "BOOLEAN"}, "source": {"scan": 3}}}}}}}, "type": "BOOLEAN"}], "type": "BOOLEAN"}, "source": {"join": {"kind": "INNER", "condition": {"operator": "=", "operand": [{"column": 17, "type": "INTEGER"}, {"column": 15, "type": "INTEGER"}], "type": "BOOLEAN"}, "left": {"join": {"kind": "INNER", "condition": {"operator": "=", "operand": [{"column": 10, "type": "INTEGER"}, {"column": 14, "type": "INTEGER"}], "type": "BOOLEAN"}, "left": {"join": {"kind": "INNER", "condition": {"operator": "AND", "operand": [{"operator": "=", "operand": [{"column": 8, "type": "BIGINT"}, {"operator": "CAST", "operand": [{"column": 9, "type": "INTEGER"}], "type": "BIGINT"}], "type": "BOOLEAN"}, {"operator": "=", "operand": [{"column": 7, "type": "VARCHAR"}, {"operator": "_ISO-8859-1'Journal::ChangesetJournal'", "operand": [], "type": "VARCHAR"}], "type": "BOOLEAN"}], "type": "BOOLEAN"}, "left": {"scan": 0}, "right": {"scan": 1}}}, "right": {"scan": 2}}}, "right": {"project": {"target": [{"column": 0, "type": "INTEGER"}], "source": {"scan": 3}}}}}}}}}}}], "help": ["LogicalSort(sort0=[$0], dir0=[DESC], fetch=[10])\n  LogicalProject(event_id=[$0], event_datetime=[$5], event_author=[$3], event_description=[$4], version=[$6], journable_id=[$2], revision=[$11], comments=[$13], committed_on=[$12], project_id=[$15], repository_type=[$16])\n    LogicalFilter(condition=[AND(=($1, 'Changeset'), =($3, 653), IN($17, {\nLogicalProject(project_id=[$1])\n  LogicalFilter(condition=[=($2, 'activity')])\n    LogicalTableScan(table=[[Cosette, enabled_modules]])\n}), IN($17, {\nLogicalAggregate(group=[{0}])\n  LogicalProject(id=[$0])\n    LogicalFilter(condition=[=($10, true)])\n      LogicalJoin(condition=[AND(=($0, $13), =($14, 'repository'), =($10, true))], joinType=[inner])\n        LogicalTableScan(table=[[Cosette, projects]])\n        LogicalTableScan(table=[[Cosette, enabled_modules]])\n}))])\n      LogicalJoin(condition=[=($17, $15)], joinType=[inner])\n        LogicalJoin(condition=[=($10, $14)], joinType=[inner])\n          LogicalJoin(condition=[AND(=($8, CAST($9):BIGINT NOT NULL), =($7, 'Journal::ChangesetJournal'))], joinType=[inner])\n            LogicalTableScan(table=[[Cosette, journals]])\n            LogicalTableScan(table=[[Cosette, changeset_journals]])\n          LogicalTableScan(table=[[Cosette, repositories]])\n        LogicalProject(id=[$0])\n          LogicalTableScan(table=[[Cosette, projects]])\n", "LogicalSort(sort0=[$0], dir0=[DESC], fetch=[10])\n  LogicalProject(event_id=[$0], event_datetime=[$5], event_author=[$3], event_description=[$4], version=[$6], journable_id=[$2], revision=[$11], comments=[$13], committed_on=[$12], project_id=[$15], repository_type=[$16])\n    LogicalFilter(condition=[AND(=($1, 'Changeset'), =($3, 653), IN($17, {\nLogicalSort(fetch=[1])\n  LogicalProject(project_id=[$1])\n    LogicalFilter(condition=[=($2, 'activity')])\n      LogicalTableScan(table=[[Cosette, enabled_modules]])\n}), IN($17, {\nLogicalSort(fetch=[1])\n  LogicalProject(id=[$0])\n    LogicalFilter(condition=[=($10, true)])\n      LogicalTableScan(table=[[Cosette, projects]])\n}))])\n      LogicalJoin(condition=[=($17, $15)], joinType=[inner])\n        LogicalJoin(condition=[=($10, $14)], joinType=[inner])\n          LogicalJoin(condition=[AND(=($8, CAST($9):BIGINT NOT NULL), =($7, 'Journal::ChangesetJournal'))], joinType=[inner])\n            LogicalTableScan(table=[[Cosette, journals]])\n            LogicalTableScan(table=[[Cosette, changeset_journals]])\n          LogicalTableScan(table=[[Cosette, repositories]])\n        LogicalProject(id=[$0])\n          LogicalTableScan(table=[[Cosette, projects]])\n"]}